{
  "updated": "09/05/2026 à 09:04 UTC",
  "count": 30,
  "articles": [
    {
      "title": "DIRECT. Chaos au Real Madrid: Arbeloa \"fier\" de ses joueurs, suivez la crise dans le vestiaire merengue en live avant le Clasico",
      "desc": "Alors qu'il se déplacera dimanche sur le terrain du Barça, dans un Clasico qui pourrait valider le titre du rival catalan en Liga, le Real Madrid s'est offert une belle crise interne cette semaine, av",
      "url": "https://rmcsport.bfmtv.com/football/liga/direct-chaos-au-real-madrid-suivez-la-crise-dans-le-vestiaire-merengue-et-la-conf-de-presse-d-arbeloa-en-live-avant-le-clasico_LN-202605090139.html",
      "image": "https://images.bfmtv.com/_c-vKh_4LirgGcmY-xYQOO63GaM=/0x74:2048x1226/800x0/images/Federico-Valverde-et-Aurelien-Tchouameni-avec-le-Real-Madrid-2283258.jpg",
      "date": "Sat, 09 May 2026 08:52:09 GMT",
      "time": "il y a < 1h",
      "source": "RMC Sport",
      "sourceId": "rmc",
      "color": "#e05252",
      "cat": "Real Madrid"
    },
    {
      "title": "Coupe du monde 2026: la fin des cours avancée de 40 jours au Mexique avant le Mondial",
      "desc": "Le ministère de l'Éducation mexicain a annoncé que la fin de l'année scolaire serait avancée de près de six semaines en raison de l'organisation de la Coupe du monde 2026 et d'une importante vague de ",
      "url": "https://rmcsport.bfmtv.com/football/coupe-du-monde/coupe-du-monde-2026-la-fin-des-cours-avancee-de-40-jours-au-mexique-avant-le-mondial_AV-202605090161.html",
      "image": "https://images.bfmtv.com/iXK0u9pIy8427M2pLAboxLMnme8=/0x27:2048x1179/800x0/images/La-presidente-mexicaine-Claudia-Sheinbaum-le-10-novembre-2025-2283269.jpg",
      "date": "Sat, 09 May 2026 08:29:36 GMT",
      "time": "il y a < 1h",
      "source": "RMC Sport",
      "sourceId": "rmc",
      "color": "#e05252",
      "cat": "Football"
    },
    {
      "title": "OM: le coup d'extincteur qui a valu à Aubameyang d'être écarté pour le match au Havre",
      "desc": "Comme indiqué par RMC Sport, l'attaquant de l'OM Pierre-Emerick Aubameyang a été écarté pour le déplacement au Havre dimanche en Ligue 1. Selon L'Equipe, c'est précisément pour avoir aspergé avec un e",
      "url": "https://rmcsport.bfmtv.com/football/clubs/olympique-marseille/om-cette-blague-qui-a-valu-a-aubameyang-d-etre-ecarte-pour-le-match-au-havre_AN-202605090154.html",
      "image": "https://images.bfmtv.com/C-FDnvY0UHB4s7ffHpjwadWkvYc=/0x140:2048x1292/800x0/images/Pierre-Emerick-Aubameyang-buteur-avec-l-OM-au-Velodrome-10-avril-2026-2268412.jpg",
      "date": "Sat, 09 May 2026 08:05:58 GMT",
      "time": "il y a < 1h",
      "source": "RMC Sport",
      "sourceId": "rmc",
      "color": "#e05252",
      "cat": "Football"
    },
    {
      "title": "Real Madrid",
      "desc": "Le Real Madrid est un club de football espagnol fondé en 1902. L'équipe de la \"Maison Blanche\", surnommée \"Merengue\" en raison de la couleur blanche du maillot, évolue dans le stade Santiago-Bernabeu.",
      "url": "https://rmcsport.bfmtv.com/football/liga/real-madrid_DN-202304140701.html",
      "image": "https://images.bfmtv.com/NqFNYHeAldzw5jJ3vYbf8CP3Nws=/0x212:2048x1364/800x0/images/Real-Madrid-1711963.jpg",
      "date": "Sat, 09 May 2026 07:29:03 GMT",
      "time": "il y a 1h",
      "source": "RMC Sport",
      "sourceId": "rmc",
      "color": "#e05252",
      "cat": "Real Madrid"
    },
    {
      "title": "Real Madrid: \"Vous voulez voir du sang?\", le coup de gueule de la compagne de Valverde après son altercation avec Tchouaméni",
      "desc": "À la suite d'une altercation avec Aurélien Tchouaméni, Federico Valverde s'est cogné la tête et souffre d'un traumatisme crânien. Alors que le joueur urugayen du Real Madrid assure que sa blessure est",
      "url": "https://rmcsport.bfmtv.com/football/liga/real-madrid-vous-voulez-voir-du-sang-le-coup-de-gueule-de-la-compagne-de-valverde-apres-son-altercation-avec-tchouameni_AN-202605090140.html",
      "image": "https://images.bfmtv.com/Q7VFQNxurQnDLojMklb8LoSpA9I=/0x20:2048x1172/800x0/images/Federico-VALVERDE-2282683.jpg",
      "date": "Sat, 09 May 2026 07:29:03 GMT",
      "time": "il y a 1h",
      "source": "RMC Sport",
      "sourceId": "rmc",
      "color": "#e05252",
      "cat": "Real Madrid"
    },
    {
      "title": "Aurélien Tchouaméni",
      "desc": "Transféré à l'été 2022 au Real Madrid pour 80 millions d'euros, Aurélien Tchouaméni, 22 ans, est la nouvelle pépite du football français au milieu de terrain. Il aura fort à faire à la Coupe du monde ",
      "url": "https://rmcsport.bfmtv.com/football/aurelien-tchouameni_DN-202211070793.html",
      "image": "https://images.bfmtv.com/D9x-X4SJA5wKluXpcoHZPdeDjYQ=/0x131:2048x1283/800x0/images/Aurelien-Tchouameni-1513175.jpg",
      "date": "Sat, 09 May 2026 07:29:03 GMT",
      "time": "il y a 1h",
      "source": "RMC Sport",
      "sourceId": "rmc",
      "color": "#e05252",
      "cat": "Football"
    },
    {
      "title": "Chaos au Real Madrid: le club annonce les sanctions pour Valverde et Tchouaméni",
      "desc": "Bagarre entre Aurélien Tchouaméni et Federico Valverde, gifle d'Antonio Rüdiger à Alvaro Carreras, escapade de Kylian Mbappé... le Real Madrid traverse actuellement une grosse zone de turbulences.",
      "url": "https://rmcsport.bfmtv.com/football/liga/direct-chaos-au-real-madrid-suivez-toutes-les-infos-sur-la-crise-qui-touche-le-club-merengue_LN-202605070645.html",
      "image": "https://images.bfmtv.com/SNpc0WhbJbid34GKWig30nafTdY=/0x48:2048x1200/800x0/images/Federico-Valverde-et-Aurelien-Tchouameni-lors-du-match-Real-Madrid-OM-en-Ligue-des-champions-le-16-09-2025-2281986.jpg",
      "date": "Sat, 09 May 2026 07:22:56 GMT",
      "time": "il y a 1h",
      "source": "RMC Sport",
      "sourceId": "rmc",
      "color": "#e05252",
      "cat": "Real Madrid"
    },
    {
      "title": "Vinicius Junior",
      "desc": "Vinícius José Paixão de Oliveira Júnior, dit Vinicius Junior ou Vinicius, est un footballeur brésilien qui évolue actuellement au Real Madrid. Né le 12 juillet 2000, il quitte son club de Flamengo en ",
      "url": "https://rmcsport.bfmtv.com/football/liga/vinicius-junior_DN-202409300526.html",
      "image": "https://images.bfmtv.com/CQ9Mb6beiV4CKLVGb9mg8HYRK_I=/0x106:2048x1258/800x0/images/Vinicius-Real-1942572.jpg",
      "date": "Sat, 09 May 2026 07:21:26 GMT",
      "time": "il y a 1h",
      "source": "RMC Sport",
      "sourceId": "rmc",
      "color": "#e05252",
      "cat": "Football"
    },
    {
      "title": "\"Un hommage à toutes les générations de supporters\": le nouveau maillot du PSG pour la saison 2026-2027 dévoilé",
      "desc": "Le Paris Saint-Germain a dévoilé samedi son maillot pour la saison 2026-2027. Avec le retour d’une large bande rouge centrale, la tunique parisienne est \"un hommage vibrant à toutes les générations de",
      "url": "https://rmcsport.bfmtv.com/football/clubs/paris-saint-germain/un-hommage-a-toutes-les-generations-de-supporters-le-nouveau-maillot-du-psg-pour-la-saison-2026-2027-devoile_AN-202605090049.html",
      "image": "https://images.bfmtv.com/r1gMLEktE-P3AbfGbmgfZMCxoHk=/13x30:1613x930/800x0/images/Marquinhos-qui-porte-le-maillot-domicile-du-PSG-pour-la-saison-2026-2027-8-mai-2026-2283189.jpg",
      "date": "Sat, 09 May 2026 07:00:00 GMT",
      "time": "il y a 2h",
      "source": "RMC Sport",
      "sourceId": "rmc",
      "color": "#e05252",
      "cat": "PSG"
    },
    {
      "title": "Lens 1-0 Nantes : Toujours le titre en tête ? “En gagnant face à Brest, le PSG validera le titre”, avoue Sage",
      "desc": "Le RC Lens s’est imposé 1-0 à Bollaert face au FC Nantes et valide son ticket pour la Ligue des Champions la saison prochaine en sécurisant la deuxième place du championnat. Interrogé sur les derniers",
      "url": "https://rmcsport.bfmtv.com/football/ligue-1/video-lens-1-0-nantes-toujours-le-titre-en-tete-en-gagnant-face-a-brest-le-psg-validera-le-titre-avoue-sage_VN-202605090131.html",
      "image": "https://images.bfmtv.com/xKE6fcJNB-qDn9ZesVYrAsv929M=/0x0:1280x720/800x0/images/Lens-1-0-Nantes-Toujours-le-titre-en-tete-En-gagnant-face-a-Brest-le-PSG-validera-le-titre-avoue-Sage-2283252.jpg",
      "date": "Sat, 09 May 2026 06:55:25 GMT",
      "time": "il y a 2h",
      "source": "RMC Sport",
      "sourceId": "rmc",
      "color": "#e05252",
      "cat": "PSG"
    },
    {
      "title": "Lens 1-0 Nantes : “Le papa est fier… L’entraîneur félicite le centre de formation”, explique Walid Mesloub",
      "desc": "L’ancien joueur du RC Lens et actuel entraîneur adjoint de la réserve Walid Mesloub s’est exprimé sur la prestation de son fils Mezian Mesloub, buteur pour son premier match en pro qui envoie le RC Le",
      "url": "https://rmcsport.bfmtv.com/football/ligue-1/video-lens-1-0-nantes-le-papa-est-fier-l-entraineur-felicite-le-centre-de-formation-explique-walid-mesloub_VN-202605090129.html",
      "image": "https://images.bfmtv.com/c8dYsoLu9tW971lPpNE-7cPISXI=/0x0:1280x720/800x0/images/Lens-1-0-Nantes-Le-papa-est-fier-L-entraineur-felicite-le-centre-de-formation-explique-Walid-Mesloub-2283251.jpg",
      "date": "Sat, 09 May 2026 06:46:55 GMT",
      "time": "il y a 2h",
      "source": "RMC Sport",
      "sourceId": "rmc",
      "color": "#e05252",
      "cat": "Football"
    },
    {
      "title": "Lens 1-0 Nantes : “Mezian Mesloub nous envoie en Ligue des champions”, sourit Sage",
      "desc": "C’est la belle histoire de la 33ème journée de Ligue 1, Mezian Mesloub, jeune joueur de la réserve du RC Lens a foulé pour la première fois la pelouse de Bollaert et pour son premier ballon il délivre",
      "url": "https://rmcsport.bfmtv.com/football/ligue-1/video-lens-1-0-nantes-walid-mesloub-nous-envoie-en-ligue-des-champions-sourit-sage_VN-202605090120.html",
      "image": "https://images.bfmtv.com/k87Vy7DCPTnOrUNjAhnc4a0126s=/0x0:1280x720/800x0/images/Lens-1-0-Nantes-Walid-Mesloub-nous-envoie-en-Ligue-des-champions-sourit-Sage-2283243.jpg",
      "date": "Sat, 09 May 2026 06:25:13 GMT",
      "time": "il y a 2h",
      "source": "RMC Sport",
      "sourceId": "rmc",
      "color": "#e05252",
      "cat": "Champions League"
    },
    {
      "title": "Lens-Nantes: Lopes a un \"sentiment de honte\" après la descente en Ligue 2",
      "desc": "Gardien et capitaine du FC Nantes, Anthony Lopes a fait part de sa \"honte\" ce vendredi soir à l'issue de la défaite contre Lens (1-0), synonyme de descente actée en Ligue 2.",
      "url": "https://rmcsport.bfmtv.com/football/ligue-1/lens-nantes-lopes-a-un-sentiment-de-honte-apres-la-descente-en-ligue-2_AV-202605090116.html",
      "image": "https://images.bfmtv.com/5wJp4VN2kmyk2upLUqDOJC1xz_c=/0x106:2048x1258/800x0/images/Anthony-Lopes-le-8-mai-2026-2283235.jpg",
      "date": "Sat, 09 May 2026 06:06:47 GMT",
      "time": "il y a 2h",
      "source": "RMC Sport",
      "sourceId": "rmc",
      "color": "#e05252",
      "cat": "Football"
    },
    {
      "title": "\"Il n’est pas interdit de rêver\": le Red Star en mission Ligue 1",
      "desc": "Et si l’Île de France comptait trois clubs franciliens en Ligue 1 la saison prochaine? À l’occasion de la 34e et dernière journée de Ligue 2 ce samedi, le Red Star (93) joue gros. Les joueurs de Saint",
      "url": "https://rmcsport.bfmtv.com/football/ligue-2/il-n-est-pas-interdit-de-rever-le-red-star-en-mission-ligue-1_AN-202605090046.html",
      "image": "https://images.bfmtv.com/kb95950VOQEMbUaE19Xw8gE5qtU=/0x212:2048x1364/800x0/images/Les-joueurs-du-Red-Star-prennent-la-pose-apres-leur-victoire-2-mai-2026-2283119.jpg",
      "date": "Sat, 09 May 2026 06:03:00 GMT",
      "time": "il y a 3h",
      "source": "RMC Sport",
      "sourceId": "rmc",
      "color": "#e05252",
      "cat": "Ligue 1"
    },
    {
      "title": "\"On va jeter toutes nos forces dans cette ultime bataille\": 50 ans après l'épopée de 1976, Saint-Etienne veut tout renverser pour retrouver la Ligue 1",
      "desc": "Dans un printemps rythmé par la douce nostalgie des années de gloire, avec la finale \"des poteaux carrés\" du 12 mai 1976 à Glasgow face au Bayern Munich en Coupe des clubs champions comme (presque) co",
      "url": "https://rmcsport.bfmtv.com/football/ligue-2/on-va-jeter-toutes-nos-forces-dans-cette-ultime-bataille-50-ans-apres-l-epopee-de-1976-saint-etienne-veut-tout-renverser-pour-retrouver-la-ligue-1_AN-202605090047.html",
      "image": "https://images.bfmtv.com/6PAHVoM_4tRkpfmrfQvDhjwMBD4=/0x156:2048x1308/800x0/images/Zuriko-Davitashvili-apres-son-but-pour-Saint-Etienne-11-avril-2026-2283126.jpg",
      "date": "Sat, 09 May 2026 05:56:00 GMT",
      "time": "il y a 3h",
      "source": "RMC Sport",
      "sourceId": "rmc",
      "color": "#e05252",
      "cat": "Ligue 1"
    },
    {
      "title": "Lens-Nantes: \"J'attendais ce petit moment\", la fierté de Walid Mesloub après l'incroyable première de son fils Mezian",
      "desc": "Buteur après quelques secondes pour ses débuts en pro, Mezian Mesloub (16 ans) a permis à Lens de battre Nantes (1-0) et de se qualifier en Ligue des champions ce vendredi. Son père Walid Mesloub, anc",
      "url": "https://rmcsport.bfmtv.com/football/ligue-1/lens-nantes-j-attendais-ce-petit-moment-la-fierte-de-walid-mesloub-apres-l-incroyable-premiere-de-son-fils-mezian_AN-202605090106.html",
      "image": "https://images.bfmtv.com/AkVVKKzGCfFx9CJDtKroGX_fbiE=/0x106:2048x1258/800x0/images/Mezian-Mesloub-le-8-mai-2026-2283232.jpg",
      "date": "Sat, 09 May 2026 05:35:35 GMT",
      "time": "il y a 3h",
      "source": "RMC Sport",
      "sourceId": "rmc",
      "color": "#e05252",
      "cat": "Football"
    },
    {
      "title": "Nantes en Ligue 2 : La honte de Lopes",
      "desc": "Après sa défaite 1-0 à Lens pour la 33e journée de Ligue 1, le FC Nantes est en Ligue 2 ce vendredi soir. Le gardien nantais Anthony Lopes a honte.",
      "url": "https://rmcsport.bfmtv.com/football/ligue-1/video-nantes-en-ligue-2-la-honte-de-lopes_VN-202605080781.html",
      "image": "https://images.bfmtv.com/V26w5NXUTLg5vM_sUuzij33aBIg=/0x0:1280x720/800x0/images/Nantes-en-Ligue-2-La-honte-de-Lopes-2283199.jpg",
      "date": "Fri, 08 May 2026 22:27:54 GMT",
      "time": "il y a 10h",
      "source": "RMC Sport",
      "sourceId": "rmc",
      "color": "#e05252",
      "cat": "Football"
    },
    {
      "title": "Nantes en L2 : \"Incapable de parler\" l'insondable tristesse de coach Vahid",
      "desc": "Le FC Nantes est en Ligue 2 après sa défaite 1-0 à Lens pour la 33e journée de Ligue 1, ce vendredi soir. Le coach nantais Vahid Halilodzic est dépité.",
      "url": "https://rmcsport.bfmtv.com/football/ligue-1/video-nantes-en-l2-incapable-de-parler-l-insondable-tristesse-de-coach-vahid_VN-202605080773.html",
      "image": "https://images.bfmtv.com/KkRW30atG2Rl7LFkQcqi1dGKbt0=/0x0:1280x720/800x0/images/Nantes-en-L2-Incapable-de-parler-l-insondable-tristesse-de-coach-Vahid-2283197.jpg",
      "date": "Fri, 08 May 2026 22:14:49 GMT",
      "time": "il y a 10h",
      "source": "RMC Sport",
      "sourceId": "rmc",
      "color": "#e05252",
      "cat": "Football"
    },
    {
      "title": "INFO RMC SPORT. OM: Aubameyang écarté pour le déplacement du Havre",
      "desc": "Pierre-Emerick Aubameyang ne sera pas du déplacement de l'OM au Havre dimanche, pour l'avant-dernière journée de Ligue 1. L'attaquant de 36 ans est écarté. Une décision qui intervient après des incide",
      "url": "https://rmcsport.bfmtv.com/football/clubs/olympique-marseille/info-rmc-sport-om-aubameyang-ecarte-pour-le-deplacement-du-havre_AP-202605080772.html",
      "image": "https://images.bfmtv.com/azGAQS5sAA5d4wywtXrcOpTn5Ac=/0x93:2048x1245/800x0/images/Pierre-Emerick-Aubameyang-attaquant-de-l-OM-a-l-echauffement-2-mai-2026-2283195.jpg",
      "date": "Fri, 08 May 2026 22:08:47 GMT",
      "time": "il y a 10h",
      "source": "RMC Sport",
      "sourceId": "rmc",
      "color": "#e05252",
      "cat": "Football"
    },
    {
      "title": "OM: Aubameyang écarté pour le déplacement du Havre",
      "desc": "Plongé dans une fin de saison chaotique, à l'image de son naufrage à Nantes (3-0) le week-end dernier, l'OM doit impérativement gagner sur la pelouse du Havre, dimanche (21h), pour se relancer dans la",
      "url": "https://rmcsport.bfmtv.com/football/clubs/olympique-marseille/direct-om-suivez-la-conference-de-presse-d-habib-beye-et-toutes-les-infos-avant-le-match-face-au-havre_LN-202605080367.html",
      "image": "https://images.bfmtv.com/azGAQS5sAA5d4wywtXrcOpTn5Ac=/0x93:2048x1245/800x0/images/Pierre-Emerick-Aubameyang-attaquant-de-l-OM-a-l-echauffement-2-mai-2026-2283195.jpg",
      "date": "Fri, 08 May 2026 22:07:24 GMT",
      "time": "il y a 10h",
      "source": "RMC Sport",
      "sourceId": "rmc",
      "color": "#e05252",
      "cat": "Football"
    },
    {
      "title": "La conférence de presse n'aura duré que quelques secondes: \"Je ne suis plus capable de parler\", la détresse de Vahid Halilodzic après la relégation de Nantes",
      "desc": "Le coach du FC Nantes Vahid Halilodzic n'a pas caché sa tristesse après la défaite à Lens ce vendredi en ouverture de la 33e journée (1-0), synonyme de relégation en Ligue 2. Le technicien a écourté s",
      "url": "https://rmcsport.bfmtv.com/football/ligue-1/la-conference-de-presse-n-aura-dure-que-quelques-secondes-je-ne-suis-plus-capable-de-parler-la-detresse-de-vahid-halilodzic-apres-la-relegation-de-nantes_AP-202605080771.html",
      "image": "https://images.bfmtv.com/Km-zhViUN5rD2xsVfLZIFhHZObs=/0x106:2048x1258/800x0/images/Vahid-Halilodzic-en-conference-de-presse-2283191.jpg",
      "date": "Fri, 08 May 2026 21:56:04 GMT",
      "time": "il y a 11h",
      "source": "RMC Sport",
      "sourceId": "rmc",
      "color": "#e05252",
      "cat": "Football"
    },
    {
      "title": "Lens-Nantes: les Sang et Or se qualifient en Ligue des champions, les Canaris descendent en Ligue 2",
      "desc": "Deuxième de Ligue 1, le RC Lens recevait le FC Nantes ce vendredi lors du match d'ouverture de la 33e journée. Bousculés, les Artésiens se sont imposés grâce à un but du jeune Mezian Mesloub (16 ans),",
      "url": "https://rmcsport.bfmtv.com/football/ligue-1/direct-lens-nantes-suivez-en-live-le-match-de-la-33e-journee-de-ligue-1_LS-202605080597.html",
      "image": "https://images.bfmtv.com/5H-h2eN32U9ECV9xxBdyE3tkUSo=/0x140:2048x1292/800x0/images/La-joie-des-joueurs-de-Lens-qui-fetent-leur-ouverture-du-score-a-Bollaert-8-mai-2026-2283182.jpg",
      "date": "Fri, 08 May 2026 21:17:52 GMT",
      "time": "il y a 11h",
      "source": "RMC Sport",
      "sourceId": "rmc",
      "color": "#e05252",
      "cat": "Champions League"
    },
    {
      "title": "Buteur à 16 ans sur son premier ballon chez les pros: l’histoire folle de Mezian Mesloub, qui envoie Lens en Ligue des champions",
      "desc": "Le RC Lens a assuré la 2e place du championnat et sa qualification directe pour la Ligue des champions en battant le FC Nantes 1-0 vendredi soir grâce à l’entrée en jeu décisive du jeune Mezian Meslou",
      "url": "https://rmcsport.bfmtv.com/football/ligue-1/buteur-a-16-ans-sur-son-premier-ballon-chez-les-pros-l-histoire-folle-de-mezian-mesloub-qui-envoie-lens-en-ligue-des-champions_AN-202605080755.html",
      "image": "https://images.bfmtv.com/nurjYQY3MfSdckiNdFqSb1fUIxk=/0x131:2048x1283/800x0/images/Mezian-Mesloub-buteur-pour-le-RC-Lens-sur-son-premier-ballon-8-mai-2026-2283183.jpg",
      "date": "Fri, 08 May 2026 20:55:22 GMT",
      "time": "il y a 12h",
      "source": "RMC Sport",
      "sourceId": "rmc",
      "color": "#e05252",
      "cat": "Champions League"
    },
    {
      "title": "Lens 1-0 Nantes : Les Nordistes en C1, les Canaris en L2, les Comms RMC",
      "desc": "Lens a battu Nantes 1-0, ce vendredi en ouverture de la 33e journée de Ligue 1. Revivez la victoire des Artésiens qui les envoie en Ligue des champions et relègue les Canaris en Ligue 2.",
      "url": "https://rmcsport.bfmtv.com/football/ligue-1/video-lens-1-0-nantes-les-nordistes-en-c1-les-canaris-en-l2-les-comms-rmc_VN-202605080752.html",
      "image": "https://images.bfmtv.com/Mdc2WCXhRT_ib3Tc5n1uPBSm6Hc=/0x0:1280x720/800x0/images/Lens-1-0-Nantes-Les-Nordistes-en-C1-les-Canaris-en-L2-les-Comms-RMC-2283181.jpg",
      "date": "Fri, 08 May 2026 20:42:35 GMT",
      "time": "il y a 12h",
      "source": "RMC Sport",
      "sourceId": "rmc",
      "color": "#e05252",
      "cat": "Football"
    },
    {
      "title": "10 mètres maximum après la ligne et un bloc qui monte tout de suite: les secrets de la demande de Luis Enrique à Safonov pour ses dégagements en touche lors de Bayern-PSG",
      "desc": "Les six-mètres tirés en touche par le gardien du PSG Matvey Safonov mercredi, lors de la qualification face au Bayern Munich en demi-finale retour de Ligue des champions, ont beaucoup fait parler. La ",
      "url": "https://rmcsport.bfmtv.com/football/clubs/paris-saint-germain/10-metres-maximum-apres-la-ligne-et-un-bloc-qui-monte-tout-de-suite-les-secrets-de-la-demande-de-luis-enrique-a-safonov-pour-ses-degagements-en-touche_AV-202605080747.html",
      "image": "https://images.bfmtv.com/zkoTrFAUSxgeYSJEvvdtHUkXBvA=/0x0:2048x1152/800x0/images/Le-gardien-du-PSG-Matvey-Safonov-face-au-Bayern-en-demi-finale-retour-de-Ligue-des-champions-le-6-mai-2026-2283113.jpg",
      "date": "Fri, 08 May 2026 20:16:54 GMT",
      "time": "il y a 12h",
      "source": "RMC Sport",
      "sourceId": "rmc",
      "color": "#e05252",
      "cat": "PSG"
    },
    {
      "title": "C'est Luis Enrique qui régale: les dessous du dîner des joueurs parisiens au lendemain de la qualification",
      "desc": "Au lendemain de leur qualification pour la finale de la Ligue des champions, les joueurs du PSG se sont retrouvés pour un dîner dans un restaurant près de l'Arc de Triomphe. Luis Enrique n'était pas p",
      "url": "https://rmcsport.bfmtv.com/football/clubs/paris-saint-germain/c-est-luis-enrique-qui-regale-les-dessous-du-diner-des-joueurs-parisiens-au-lendemain-de-la-qualification_AN-202605080741.html",
      "image": "https://images.bfmtv.com/KBboZk4nh3ymuN1tGcKoOqb29Wg=/0x202:2048x1354/800x0/images/Luis-Enrique-celebre-la-qualification-du-PSG-en-finale-de-la-Ligue-des-champions-apres-le-nul-sur-le-terrain-du-Bayern-Munich-1-1-le-6-mai-2026-2282072.jpg",
      "date": "Fri, 08 May 2026 19:45:30 GMT",
      "time": "il y a 13h",
      "source": "RMC Sport",
      "sourceId": "rmc",
      "color": "#e05252",
      "cat": "Football"
    },
    {
      "title": "Chambres retournées, extincteur vidé…. Des joueurs de l’OM sont-ils partis en vrille lors de la dernière soirée de la mise au vert à la Commanderie?",
      "desc": "Selon Foot Mercato, des joueurs de l’OM se sont amusés à semer la pagaille à la Commanderie jeudi soir lors d’une fête improvisée pour leur dernière soirée de mise au vert. Cet esprit \"colonie de vaca",
      "url": "https://rmcsport.bfmtv.com/football/clubs/olympique-marseille/chambres-retournes-extincteur-vide-des-joueurs-de-l-om-sont-ils-partis-en-vrille-lors-de-la-derniere-soiree-de-la-mise-au-vert-a-la-commanderie_AV-202605080739.html",
      "image": "https://images.bfmtv.com/8M8h0JIoDShUef7_8uq0aqieG3I=/0x165:2048x1317/800x0/images/Les-joueurs-de-l-OM-face-a-Metz-le-10-avril-2026-au-stade-Velodrome-2283165.jpg",
      "date": "Fri, 08 May 2026 19:24:00 GMT",
      "time": "il y a 13h",
      "source": "RMC Sport",
      "sourceId": "rmc",
      "color": "#e05252",
      "cat": "Football"
    },
    {
      "title": "Chaos au Real Madrid: \"Il y en a qui se comportent comme des enfants\", joueurs, supporters, dirigeants... tout le monde est au bout du rouleau",
      "desc": "L’altercation entre Aurélien Tchouaméni et Federico Valverde est le point culminant d’une saison sous haute tension à Madrid. Avant le Clasico, le club est coincé dans une crise sans fin.",
      "url": "https://rmcsport.bfmtv.com/football/liga/chaos-au-real-madrid-il-y-en-a-qui-se-comportent-comme-des-enfants-joueurs-supporters-dirigeants-tout-le-monde-est-au-bout-du-rouleau_AN-202605080732.html",
      "image": "https://images.bfmtv.com/j-9Y3GQPciLN6DE6b60_sRdhTus=/0x0:2048x1152/800x0/images/Trent-Alexander-Arnold-lateral-du-Real-Madrid-3-mai-2026-2283166.jpg",
      "date": "Fri, 08 May 2026 19:10:13 GMT",
      "time": "il y a 13h",
      "source": "RMC Sport",
      "sourceId": "rmc",
      "color": "#e05252",
      "cat": "Real Madrid"
    },
    {
      "title": "Après l'échec en Coupe d'Europe, quel avenir pour Strasbourg?",
      "desc": "Demi-finaliste de Coupe de France et de Ligue Europa Conférence, Strasbourg a finalement raté le coche. Sa 8e place actuelle en Ligue 1, à deux journées de la fin du championnat, laisse présager une s",
      "url": "https://rmcsport.bfmtv.com/football/clubs/rc-strasbourg/apres-l-echec-en-coupe-d-europe-quel-avenir-pour-strasbourg_AN-202605080710.html",
      "image": "https://images.bfmtv.com/t262rCyno5zWIN5Cx8gPTU8qoi8=/0x212:2048x1364/800x0/images/Enciso-et-les-joueurs-de-Strasbourg-decus-apres-leur-elimination-en-demi-finale-de-Ligue-Conference-7-mai-2026-2283141.jpg",
      "date": "Fri, 08 May 2026 17:57:55 GMT",
      "time": "il y a 15h",
      "source": "RMC Sport",
      "sourceId": "rmc",
      "color": "#e05252",
      "cat": "Football"
    },
    {
      "title": "\"Je suis amoureux de cet entraîneur!\": la superbe déclaration d’amour de Jérôme Rothen à Luis Enrique",
      "desc": "Deux jours après la qualification du PSG pour sa deuxième finale de Ligue des champions consécutives, Jérôme Rothen s’est montré dithyrambique au sujet de l’entraîneur parisien Luis Enrique. \"J’en ai ",
      "url": "https://rmcsport.bfmtv.com/football/clubs/paris-saint-germain/je-suis-amoureux-de-cet-entraineur-la-superbe-declaration-d-amour-de-jerome-rothen-a-luis-enrique_AV-202605080709.html",
      "image": "https://images.bfmtv.com/-tzdBRCH1qq87KuD9HXkpsuIf0w=/0x52:2032x1195/800x0/images/La-joie-de-l-entraineur-parisien-Luis-Enrique-apres-la-qualification-du-PSG-en-finale-de-la-Ligue-des-champions-face-au-Bayern-le-6-mai-2026-2283137.jpg",
      "date": "Fri, 08 May 2026 17:57:42 GMT",
      "time": "il y a 15h",
      "source": "RMC Sport",
      "sourceId": "rmc",
      "color": "#e05252",
      "cat": "Football"
    }
  ],
  "scores": []
}