{
  "updated": "10/05/2026 à 14:13 UTC",
  "count": 30,
  "articles": [
    {
      "title": "Real Madrid",
      "desc": "Le Real Madrid est un club de football espagnol fondé en 1902. L'équipe de la \"Maison Blanche\", surnommée \"Merengue\" en raison de la couleur blanche du maillot, évolue dans le stade Santiago-Bernabeu.",
      "url": "https://rmcsport.bfmtv.com/football/liga/real-madrid_DN-202304140701.html",
      "image": "https://images.bfmtv.com/NqFNYHeAldzw5jJ3vYbf8CP3Nws=/0x212:2048x1364/800x0/images/Real-Madrid-1711963.jpg",
      "date": "Sun, 10 May 2026 14:08:28 GMT",
      "time": "il y a < 1h",
      "source": "RMC Sport",
      "sourceId": "rmc",
      "color": "#e05252",
      "cat": "Real Madrid"
    },
    {
      "title": "FC Barcelone",
      "desc": "Le FC Barcelone, ou Barça, est un club de football espagnol fondé en 1899, situé en Catalogne. L'équipe, surnommée Blaugrana, évolue au Camp Nou, stade de près de 100.000 places. A son palmarès, 26 ti",
      "url": "https://rmcsport.bfmtv.com/football/liga/fc-barcelone_DN-202304140698.html",
      "image": "https://images.bfmtv.com/9RlYYrwPx8Cl-3M46D37jm9R6rg=/4x78:1428x879/800x0/images/Les-joueurs-du-FC-Barcelone-face-au-Rayo-Vallecano-le-25-novembre-2023-1757008.jpg",
      "date": "Sun, 10 May 2026 14:08:28 GMT",
      "time": "il y a < 1h",
      "source": "RMC Sport",
      "sourceId": "rmc",
      "color": "#e05252",
      "cat": "Football"
    },
    {
      "title": "DIRECT. Barça-Real: suivez le bouillant Clasico en live",
      "desc": "Bien installé en tête de la Liga, le FC Barcelone a l'opportunité dimanche de remporter un 29e titre de champion d'Espagne lors d'un Clasico décisif, et d'enfoncer un peu plus le Real Madrid de Kylian",
      "url": "https://rmcsport.bfmtv.com/football/liga/direct-barca-real-suivez-le-bouillant-clasico-en-live_LS-202605100266.html",
      "image": "https://images.bfmtv.com/GTCggU4nSblxRS1OwpAFK7uGXKI=/0x106:2048x1258/800x0/images/Raphinha-face-a-Raul-Asencio-lors-de-Barca-Real-Madrid-le-11-janvier-2026-2283609.jpg",
      "date": "Sun, 10 May 2026 14:08:18 GMT",
      "time": "il y a < 1h",
      "source": "RMC Sport",
      "sourceId": "rmc",
      "color": "#e05252",
      "cat": "Football"
    },
    {
      "title": "OL: \"Il manque le trophée du coeur\", les confidences de Corentin Tolisso sur son avenir",
      "desc": "Interrogé sur son avenir par Alexandre Lacazette dans \"Téléfoot\" sur TF1 ce dimanche, Corentin Tolisso a mis fin à toute spéculation avant même que l'une puisse naître. Le capitaine de l'Olympique lyo",
      "url": "https://rmcsport.bfmtv.com/football/clubs/olympique-lyon/transferts/ol-il-manque-le-trophee-du-coeur-les-confidences-de-corentin-tolisso-sur-son-avenir_AV-202605100262.html",
      "image": "https://images.bfmtv.com/fdR0d4x5XWGk3uxu8iWc-h57tfY=/107x295:1995x1357/800x0/images/Corentin-TOLISSO-apres-le-match-OL-Celta-le-19-03-2026-2256049.jpg",
      "date": "Sun, 10 May 2026 13:58:20 GMT",
      "time": "il y a < 1h",
      "source": "RMC Sport",
      "sourceId": "rmc",
      "color": "#e05252",
      "cat": "Football"
    },
    {
      "title": "DIRECT. PSG-Brest: suivez en live le match de la 33e journée de Ligue 1",
      "desc": "Encore sur son petit nuage après l'accession en finale de la Ligue des champions, le PSG doit redescendre sur terre face à Brest, dimanche au Parc des Princes où un succès lui offrirait quasiment le 1",
      "url": "https://rmcsport.bfmtv.com/football/ligue-1/direct-psg-brest-suivez-en-live-le-match-de-la-33e-journee-de-ligue-1_LS-202605100247.html",
      "image": "https://images.bfmtv.com/5a-JEmYW7JPNFpr6Ap-1d_ItFrc=/0x144:2048x1296/800x0/images/La-joie-des-joueurs-parisiens-lors-du-match-Bayern-PSG-1-1-le-6-mai-2026-2282154.jpg",
      "date": "Sun, 10 May 2026 13:48:01 GMT",
      "time": "il y a < 1h",
      "source": "RMC Sport",
      "sourceId": "rmc",
      "color": "#e05252",
      "cat": "Ligue 1"
    },
    {
      "title": "Real Madrid: \"De la pure spéculation\", José Mourinho dément tout contact avec le club malgré les rumeurs",
      "desc": "Alors que le Real Madrid est en pleine crise, les Merengues cherchent activement un successeur à Alvaro Arbeloa. Ces derniers jours, le nom de José Mourinho est ressorti dans la presse espagnole afin ",
      "url": "https://rmcsport.bfmtv.com/football/liga/real-madrid-de-la-pure-speculation-jose-mourinho-dement-tout-contact-avec-le-club-malgre-les-rumeurs_AV-202605100261.html",
      "image": "https://images.bfmtv.com/7X-RKgs4a5Efteo_Pn4siopZ4xM=/0x106:2048x1258/800x0/images/Jose-Mourinho-lors-du-match-de-Serie-A-entre-la-Roma-et-la-Juventus-le-9-janvier-2022-2283604.jpg",
      "date": "Sun, 10 May 2026 13:47:14 GMT",
      "time": "il y a < 1h",
      "source": "RMC Sport",
      "sourceId": "rmc",
      "color": "#e05252",
      "cat": "Real Madrid"
    },
    {
      "title": "Jose Mourinho",
      "desc": "José Mário dos Santos Mourinho Félix, plus couramment appelé José Mourinho, né le 26 janvier 1963 à Setúbal, est un charismatique entraîneur de football portugais. Vainqueur de la Ligue des champions ",
      "url": "https://rmcsport.bfmtv.com/football/jose-mourinho_DN-202108310520.html",
      "image": "https://images.bfmtv.com/vDHcXqo8QBQKpP9cxKofnfCGW-I=/0x0:2048x1152/800x0/images/Jose-Mourinho-1017271.jpg",
      "date": "Sun, 10 May 2026 13:47:14 GMT",
      "time": "il y a < 1h",
      "source": "RMC Sport",
      "sourceId": "rmc",
      "color": "#e05252",
      "cat": "Football"
    },
    {
      "title": "DIRECT. Le Havre-OM: suivez en live le match de la 33e journée de Ligue 1",
      "desc": "En plein marasme, l'OM veut oublier le psychodrame vécu lors de leur mise au vert cette semaine pour tenter de sauver une saison qui pourrait les voir sans qualification européenne.",
      "url": "https://rmcsport.bfmtv.com/football/ligue-1/direct-le-havre-om-suivez-en-live-le-match-de-la-33e-journee-de-ligue-1_LS-202605100255.html",
      "image": "https://images.bfmtv.com/8M8h0JIoDShUef7_8uq0aqieG3I=/0x165:2048x1317/800x0/images/Les-joueurs-de-l-OM-face-a-Metz-le-10-avril-2026-au-stade-Velodrome-2283165.jpg",
      "date": "Sun, 10 May 2026 13:29:44 GMT",
      "time": "il y a < 1h",
      "source": "RMC Sport",
      "sourceId": "rmc",
      "color": "#e05252",
      "cat": "Ligue 1"
    },
    {
      "title": "OM: \"Les enfermer 4 jours, ça ne va pas les faire courir plus\": le coup de gueule de Di Meco contre les \"punitions stupides\" envers les joueurs",
      "desc": "En marge du déplacement au Havre dimanche soir (21h), Eric Di Meco a jugé \"stupides\" les sanctions infligées aux joueurs de l'OM et la mise au vert forcée de quatre jours après leur déroute à Nantes (",
      "url": "https://rmcsport.bfmtv.com/football/clubs/olympique-marseille/om-les-enfermer-4-jours-ca-ne-va-pas-les-faire-courir-plus-di-meco-ne-comprend-pas-les-punitions-stupides-envers-les-joueurs_AV-202605100252.html",
      "image": "https://images.bfmtv.com/k2Gc0JR7PveRmg6vi3mq82J5kD4=/0x106:2048x1258/800x0/images/Pierre-Emerick-Aubameyang-lors-de-Nantes-OM-le-2-mai-2026-2283579.jpg",
      "date": "Sun, 10 May 2026 13:22:25 GMT",
      "time": "il y a < 1h",
      "source": "RMC Sport",
      "sourceId": "rmc",
      "color": "#e05252",
      "cat": "Football"
    },
    {
      "title": "Barça-Real Madrid: Hansi Flick apprend le décès de son père juste avant le Clasico",
      "desc": "Le coach du FC Barcelone Hansi Flick a perdu son père ce dimanche matin, avant le Clasico face au Real Madrid (21h). L’entraîneur allemand a informé sa direction et son vestiaire de la triste nouvelle",
      "url": "https://rmcsport.bfmtv.com/football/liga/barca-real-madrid-hansi-flick-apprend-le-deces-de-son-pere-juste-avant-le-clasico_AV-202605100237.html",
      "image": "https://images.bfmtv.com/ljsHlQSDo-5mJeDd9uTBgtdYa3g=/0x0:2048x1152/800x0/images/Hansi-Flick-lors-d-une-conference-de-presse-avant-le-Clasico-le-9-mai-2026-2283588.jpg",
      "date": "Sun, 10 May 2026 12:56:42 GMT",
      "time": "il y a 1h",
      "source": "RMC Sport",
      "sourceId": "rmc",
      "color": "#e05252",
      "cat": "Real Madrid"
    },
    {
      "title": "DIRECT. Avant-match Barça-Real Madrid: Flick a appris la mort de son père ce dimanche matin",
      "desc": "Alors qu'il se déplacera dimanche sur le terrain du Barça, dans un Clasico qui pourrait valider le titre du rival catalan en Liga, le Real Madrid s'est offert une belle crise interne cette semaine, av",
      "url": "https://rmcsport.bfmtv.com/football/liga/direct-chaos-au-real-madrid-suivez-la-crise-dans-le-vestiaire-merengue-et-la-conf-de-presse-d-arbeloa-en-live-avant-le-clasico_LN-202605090139.html",
      "image": "https://images.bfmtv.com/_jha3QHYHt-H1q1F6zfTF31LcNo=/0x0:2048x1152/800x0/images/Hansi-Flick-lors-de-la-demi-finale-aller-de-la-Coupe-du-roi-entre-l-Atletico-de-Madrid-et-le-Barca-le-12-fevrier-2026-2235251.jpg",
      "date": "Sun, 10 May 2026 12:37:13 GMT",
      "time": "il y a 1h",
      "source": "RMC Sport",
      "sourceId": "rmc",
      "color": "#e05252",
      "cat": "Real Madrid"
    },
    {
      "title": "Benfica : \"Aucun contact avec le Real Madrid\", Mourinho dénonce les \"spéculations\" à son sujet",
      "desc": "Cité pour prendre la suite d'Alvaro Arbeloa au Real Madrid, José Mourinho a remis l'église au milieu du village ce dimanche en conférence de presse. Selon le Special One, toutes les informations sorti",
      "url": "https://rmcsport.bfmtv.com/football/liga/video-benfica-aucun-contact-avec-le-real-madrid-mourinho-denonce-les-speculations-a-son-sujet_VN-202605100229.html",
      "image": "https://images.bfmtv.com/AP1QWwbn5WyLn2lAunlXeieItxU=/0x0:1280x720/800x0/images/Benfica-Aucun-contact-avec-le-Real-Madrid-Mourinho-denonce-les-speculations-a-son-sujet-2283582.jpg",
      "date": "Sun, 10 May 2026 12:22:30 GMT",
      "time": "il y a 1h",
      "source": "RMC Sport",
      "sourceId": "rmc",
      "color": "#e05252",
      "cat": "Real Madrid"
    },
    {
      "title": "Le Havre - OM : \"Des punitions stupides\", Di Meco agacé par des mises au vert inutiles",
      "desc": "Déjà décroché pour se qualifier directement en Ligue des champions, l'OM peut encore espérer rallier une Coupe d'Europe la saison prochaine. Mais son destin ne dépend pas que de lui. Les Marseillais q",
      "url": "https://rmcsport.bfmtv.com/football/video-le-havre-om-des-punitions-stupides-di-meco-agace-par-des-mises-au-vert-inutiles_VN-202605100221.html",
      "image": "https://images.bfmtv.com/BHMxpP9a5xCfJpDvnZf0s8S5qKw=/0x0:1280x720/800x0/images/Le-Havre-OM-Des-punitions-stupides-Di-Meco-agace-par-des-mises-au-vert-inutiles-2283574.jpg",
      "date": "Sun, 10 May 2026 11:37:40 GMT",
      "time": "il y a 2h",
      "source": "RMC Sport",
      "sourceId": "rmc",
      "color": "#e05252",
      "cat": "Football"
    },
    {
      "title": "Barça-Real: les dessous du forfait de Mbappé pour le Clasico",
      "desc": "Absent du groupe du Real Madrid pour le Clasico face au Barça dimanche soir au Camp Nou (21h), l’attaquant français Kylian Mbappé espérait pouvoir jouer face aux Catalans avant de ressentir une gêne a",
      "url": "https://rmcsport.bfmtv.com/football/kylian-mbappe/barca-real-les-dessous-du-forfait-de-mbappe-pour-le-clasico_AV-202605100220.html",
      "image": "https://images.bfmtv.com/3TYDzZzTP4k9UzyOqMH8iMC6FEI=/6x0:2038x1143/800x0/images/Kylian-Mbappe-a-l-entrainement-du-Real-Madrid-le-6-avril-2026-2283573.jpg",
      "date": "Sun, 10 May 2026 11:31:02 GMT",
      "time": "il y a 2h",
      "source": "RMC Sport",
      "sourceId": "rmc",
      "color": "#e05252",
      "cat": "Football"
    },
    {
      "title": "\"Ça a créé une polémique autour de qui choisit\": Pierre Sage encore frustré par le report de PSG-Lens",
      "desc": "Interrogé dans l’émission Téléfoot, diffusée ce dimanche, le coach du RC Lens Pierre Sage s’est exprimé sur sa saison à la tête du club nordiste. Malgré une belle deuxième place acquise à sa cause, le",
      "url": "https://rmcsport.bfmtv.com/football/ligue-1/ca-a-cree-une-polemique-autour-de-qui-choisit-pierre-sage-encore-frustre-par-le-report-de-psg-lens_AV-202605100216.html",
      "image": "https://images.bfmtv.com/rfHHXWzlQm6hsyZDSdXngoaB7hY=/0x106:2048x1258/800x0/images/Pierre-Sage-lors-du-match-de-Ligue-1-entre-Lens-et-Nantes-le-8-mai-2026-2283567.jpg",
      "date": "Sun, 10 May 2026 11:20:58 GMT",
      "time": "il y a 2h",
      "source": "RMC Sport",
      "sourceId": "rmc",
      "color": "#e05252",
      "cat": "PSG"
    },
    {
      "title": "Ousmane Dembélé",
      "desc": "Ousmane Dembélé est un footballeur international français né à Vernon en 1997. Jeune surdoué formé en Normandie et au stade rennais, il explose à Dortmund avant de rejoindre le FC Barcelone pour palli",
      "url": "https://rmcsport.bfmtv.com/football/ousmane-dembele_DN-202210100814.html",
      "image": "https://images.bfmtv.com/yQ63Qv_k5XnYSl7MJSzfr0Fnf6M=/0x8:2048x1160/800x0/images/Ousmane-Dembele-1476590.jpg",
      "date": "Sun, 10 May 2026 10:46:17 GMT",
      "time": "il y a 3h",
      "source": "RMC Sport",
      "sourceId": "rmc",
      "color": "#e05252",
      "cat": "Football"
    },
    {
      "title": "Des animations surprises attendues: le CUP va fêter ses 10 ans au Parc des Princes contre Brest",
      "desc": "Un moment de fête sera célébré ce dimanche au Parc des Princes. A l’occasion de la réception de Brest, dans le cadre de la 33e journée de Ligue 1, le Collectif Ultras Paris (CUP) célébrera ses dix ans",
      "url": "https://rmcsport.bfmtv.com/football/clubs/paris-saint-germain/des-animations-surprises-attendues-le-cup-va-feter-ses-10-ans-au-parc-des-princes-contre-brest_AV-202605100206.html",
      "image": "https://images.bfmtv.com/PYDCN7DcelRjredERq-ckq0dbYI=/0x115:2048x1267/800x0/images/Les-supporters-du-PSG-du-Collectif-Ultra-Paris-au-stade-Oceane-face-au-Havre-le-28-fevrier-2026-2276074.jpg",
      "date": "Sun, 10 May 2026 10:46:16 GMT",
      "time": "il y a 3h",
      "source": "RMC Sport",
      "sourceId": "rmc",
      "color": "#e05252",
      "cat": "Football"
    },
    {
      "title": "Barça-Real Madrid: Mbappé finalement absent pour le Clasico, Tchouaméni bien présent malgré l'altercation avec Valverde",
      "desc": "À quelques heures de disputer un Clasico qui pourrait sacrer le Barça en Liga (21h), le Real Madrid a communiqué son groupe ce dimanche. Incertain, Kylian Mbappé sera finalement absent, tandis qu'Auré",
      "url": "https://rmcsport.bfmtv.com/football/liga/barca-real-mbappe-finalement-absent-pour-le-clasico-tchouameni-bien-present-malgre-l-altercation-avec-valverde_AN-202605100189.html",
      "image": "https://images.bfmtv.com/XRtQXh0Btf4kfztbVnaVxK3lQ0U=/0x143:2048x1295/800x0/images/Kylian-Mbappe-avec-le-Real-Madrid-le-10-avril-2026-2281375.jpg",
      "date": "Sun, 10 May 2026 10:09:48 GMT",
      "time": "il y a 4h",
      "source": "RMC Sport",
      "sourceId": "rmc",
      "color": "#e05252",
      "cat": "Real Madrid"
    },
    {
      "title": "Aurélien Tchouaméni",
      "desc": "Transféré à l'été 2022 au Real Madrid pour 80 millions d'euros, Aurélien Tchouaméni, 22 ans, est la nouvelle pépite du football français au milieu de terrain. Il aura fort à faire à la Coupe du monde ",
      "url": "https://rmcsport.bfmtv.com/football/aurelien-tchouameni_DN-202211070793.html",
      "image": "https://images.bfmtv.com/D9x-X4SJA5wKluXpcoHZPdeDjYQ=/0x131:2048x1283/800x0/images/Aurelien-Tchouameni-1513175.jpg",
      "date": "Sun, 10 May 2026 10:09:48 GMT",
      "time": "il y a 4h",
      "source": "RMC Sport",
      "sourceId": "rmc",
      "color": "#e05252",
      "cat": "Football"
    },
    {
      "title": "Incidents à Bastia: Le Mans fixé mercredi sur sa montée en Ligue 1",
      "desc": "Après l’interruption du match entre Bastia et Le Mans samedi lors de la dernière journée de Ligue 2, la commission de discipline de la LFP annonce dimanche matin qu’elle met en instruction ces inciden",
      "url": "https://rmcsport.bfmtv.com/football/ligue-2/incidents-a-bastia-le-mans-fixe-mercredi-sur-sa-montee-en-ligue-1_AV-202605100176.html",
      "image": "https://images.bfmtv.com/m6vGCmVgUp6E4dng1SRGC1XyEnw=/0x150:2048x1302/800x0/images/Les-joueurs-du-Mans-face-a-Bastia-le-9-mai-2026-a-Furiani-2283544.jpg",
      "date": "Sun, 10 May 2026 09:40:33 GMT",
      "time": "il y a 4h",
      "source": "RMC Sport",
      "sourceId": "rmc",
      "color": "#e05252",
      "cat": "Ligue 1"
    },
    {
      "title": "Fumigènes, terrain envahi, joueurs évacués... le derby de Prague part en vrille",
      "desc": "Scènes de chaos incroyables lors du derby Slavia-Sparta. Alors que le club qui accueillait se dirigeait vers un nouveau titre de champion, le terrain a été envahi avant la fin du match (3-2). Des diza",
      "url": "https://rmcsport.bfmtv.com/football/video-fumigenes-terrain-envahi-joueurs-evacues-le-derby-de-prague-part-en-vrille_VN-202605100173.html",
      "image": "https://images.bfmtv.com/tiJmcdMfBs2x1z4S2hrdldnbGp8=/0x0:1280x720/800x0/images/Fumigenes-terrain-envahi-joueurs-evacues-le-derby-de-Prague-part-en-vrille-2283543.jpg",
      "date": "Sun, 10 May 2026 09:27:11 GMT",
      "time": "il y a 4h",
      "source": "RMC Sport",
      "sourceId": "rmc",
      "color": "#e05252",
      "cat": "Football"
    },
    {
      "title": "PSG-Brest: Safonov présent, Zaïre-Emery absent... un groupe parisien remanié pour la dernière à domicile",
      "desc": "Plusieurs joueurs cadres du PSG manqueront la réception du Stade Brestois ce dimanche 10 mai (21 heures), calée entre la demie retour de C1 contre le Bayern Munich et le match en retard à Lens. Au cou",
      "url": "https://rmcsport.bfmtv.com/football/clubs/paris-saint-germain/psg-brest-safonov-present-zaire-emery-absent-un-groupe-parisien-remanie-pour-la-derniere-a-domicile_AV-202605100167.html",
      "image": "https://images.bfmtv.com/5a-JEmYW7JPNFpr6Ap-1d_ItFrc=/0x144:2048x1296/800x0/images/La-joie-des-joueurs-parisiens-lors-du-match-Bayern-PSG-1-1-le-6-mai-2026-2282154.jpg",
      "date": "Sun, 10 May 2026 09:18:26 GMT",
      "time": "il y a 4h",
      "source": "RMC Sport",
      "sourceId": "rmc",
      "color": "#e05252",
      "cat": "PSG"
    },
    {
      "title": "Ligue 2: le sort de Bastia-Le Mans tranché le 13 mai",
      "desc": "Pas maître de son destin avant la dernière journée de Ligue 2, Saint-Étienne a conclu la saison régulière par un festival face à Amiens dans l’espoir de rejoindre directement la Ligue 1 (5-0). Mais da",
      "url": "https://rmcsport.bfmtv.com/football/ligue-2/direct-saint-etienne-amiens-suivez-le-match-de-la-derniere-journee-de-ligue-2-en-live_LS-202605090292.html",
      "image": "https://images.bfmtv.com/ckKz1Ltm8Oa9rjc6BZ2K2M8dz6g=/0x106:2048x1258/800x0/images/Le-Mans-2283434.jpg",
      "date": "Sun, 10 May 2026 09:12:51 GMT",
      "time": "il y a 5h",
      "source": "RMC Sport",
      "sourceId": "rmc",
      "color": "#e05252",
      "cat": "Football"
    },
    {
      "title": "\"Ce lâche raciste m'a traité de singe\": le joueur de l'Udinese, Keinan Davis, accuse, en le nommant, un joueur de Cagliari de propos racistes",
      "desc": "Dans une story sur Instagram, l'attaquant de l'Udinese, Keinan Davis, a nommément accusé son adversaire de Cagliari, Alberto Dossena, de l'avoir insulté de \"singe\" lors de leur match de Serie A samedi",
      "url": "https://rmcsport.bfmtv.com/football/serie-a/ce-lache-raciste-m-a-traite-de-singe-le-joueur-de-l-udinese-keinan-davis-accuse-en-le-nommant-un-joueur-de-cagliari-de-propos-racistes_AV-202605100145.html",
      "image": "https://images.bfmtv.com/D7QfRn2uDMOYl2vMQp_xa7_ZHjI=/0x50:2048x1202/800x0/images/Keinan-Davis-et-Alberto-Dossena-lors-du-match-de-Serie-A-entre-l-Udinese-et-Cagliari-le-9-mai-2026-2283515.jpg",
      "date": "Sun, 10 May 2026 08:20:09 GMT",
      "time": "il y a 5h",
      "source": "RMC Sport",
      "sourceId": "rmc",
      "color": "#e05252",
      "cat": "Football"
    },
    {
      "title": "\"Au début, les joueurs m’ont pris pour un fou\": l’émotion du coach du Mans, Patrick Videira, en attendant l’officialisation de la montée en Ligue 1",
      "desc": "Après l’interruption du match à Bastia et avant un retour triomphal dans la Sarthe dans la nuit de samedi à dimanche, l’entraîneur du Mans, Patrick Videira, était invité de l'After Foot sur RMC pour p",
      "url": "https://rmcsport.bfmtv.com/football/ligue-2/au-debut-les-joueurs-m-ont-pris-pour-un-fou-l-emotion-du-coach-du-mans-patrick-videira-en-attendant-l-officialisation-de-la-montee-en-ligue-1_AV-202605100137.html",
      "image": "https://images.bfmtv.com/R8g4bemd6q5BQeCvVon2lEmmQMw=/0x110:2048x1262/800x0/images/L-entraineur-du-Mans-Patrick-Videira-lors-du-match-de-Ligue-2-contre-Reims-le-2-mai-2026-2283518.jpg",
      "date": "Sun, 10 May 2026 07:51:39 GMT",
      "time": "il y a 6h",
      "source": "RMC Sport",
      "sourceId": "rmc",
      "color": "#e05252",
      "cat": "Ligue 1"
    },
    {
      "title": "Stade Briochin 3-0 QRM : Le retourné acrobatique magique d'Achahbar",
      "desc": "Le milieu offensif du Stade Briochin Karim Achahbar a inscrit un but magique ce samedi lors de la victoire 3-0 de son équipe face à Quevilly. Un retourné acrobatique de toute beauté.",
      "url": "https://rmcsport.bfmtv.com/football/video-stade-briochin-3-0-qrm-le-retourne-acrobatique-magique-d-achahbar_VN-202605100125.html",
      "image": "https://images.bfmtv.com/g7gbr8wrMigCfCK3VwRXXRMdYdY=/0x0:1280x720/800x0/images/Stade-Briochin-3-0-QRM-Le-retourne-acrobatique-magique-d-Achahbar-2283509.jpg",
      "date": "Sun, 10 May 2026 07:12:16 GMT",
      "time": "il y a 7h",
      "source": "RMC Sport",
      "sourceId": "rmc",
      "color": "#e05252",
      "cat": "Football"
    },
    {
      "title": "Ligue 2: la très grosse fête des joueurs du Mans accueillis en héros malgré leur montée pas encore officielle",
      "desc": "Sur le coup de quatre heures du matin, des centaines de supporters se sont rassemblés au centre d'entraînement du Mans pour fêter leurs joueurs malgré le flou autour de leur montée en Ligue 1. Quelque",
      "url": "https://rmcsport.bfmtv.com/football/ligue-2/ligue-2-la-tres-grosse-fete-des-joueurs-du-mans-accueillis-en-heros-malgre-leur-montee-pas-encore-officielle_AV-202605100119.html",
      "image": "https://images.bfmtv.com/6HRmkwybzJJ1PScoAMuIQBPtTAo=/0x0:1280x720/800x0/images/Les-joueurs-du-Mans-fetent-la-remontee-du-club-en-Ligue-1-le-10-mai-2026-2283521.jpg",
      "date": "Sun, 10 May 2026 07:03:17 GMT",
      "time": "il y a 7h",
      "source": "RMC Sport",
      "sourceId": "rmc",
      "color": "#e05252",
      "cat": "Football"
    },
    {
      "title": "La folie au Mans en attendant l'officialisation de la montée en Ligue 1",
      "desc": "Les joueurs du Mans ont été accueillis dans une ambiance folle ce dimanche à 3h45 au centre d'entrainement du club sarthois. Le Mans, qui menait 2-0 à Bastia vendredi avant l'interruption de la rencon",
      "url": "https://rmcsport.bfmtv.com/football/video-la-folie-au-mans-en-attendant-l-officialisation-de-la-montee-en-ligue-1_VN-202605100111.html",
      "image": "https://images.bfmtv.com/5_Yhce5umS8NG01ykrFiIH95QrA=/0x0:1280x720/800x0/images/La-folie-au-Mans-en-attendant-l-officialisation-de-la-montee-en-Ligue-1-2283502.jpg",
      "date": "Sun, 10 May 2026 06:36:16 GMT",
      "time": "il y a 7h",
      "source": "RMC Sport",
      "sourceId": "rmc",
      "color": "#e05252",
      "cat": "Ligue 1"
    },
    {
      "title": "Le Havre - Marseille en direct : sur quelle chaîne et à quelle heure regarder le match de Ligue 1 ?",
      "desc": "Le stade Océane s’apprête à vibrer. D’un côté, Le Havre aborde cette rencontre avec la sérénité d’une équipe qui n’a plus grand chose à craindre. De l’autre, l’Olympique de Marseille se déplace en ple",
      "url": "https://rmcsport.bfmtv.com/football/ligue-1/le-havre-marseille-en-direct-sur-quelle-chaine-et-a-quelle-heure-regarder-le-match-de-ligue-1_AN-202605100018.html",
      "image": "https://images.bfmtv.com/-u9J_aQtyunmq0A3HCmVaGLuZD0=/0x0:1600x900/800x0/images/Le-Havre-Marseille-en-direct-sur-quelle-chaine-et-a-quelle-heure-regarder-le-match-de-Ligue-1-2281866.jpg",
      "date": "Sun, 10 May 2026 04:40:00 GMT",
      "time": "il y a 9h",
      "source": "RMC Sport",
      "sourceId": "rmc",
      "color": "#e05252",
      "cat": "Ligue 1"
    },
    {
      "title": "FC Barcelone - Real Madrid en direct : à quelle heure et sur quelle chaîne regarder le match de Liga ?",
      "desc": "Arrêtez tout ! Ce dimanche, le Spotify Camp Nou s’apprête à accueillir un Clasico brûlant, peut-être décisif pour le titre. Le calcul est simple : si le FC Barcelone s’impose ou obtient un nul, il ser",
      "url": "https://rmcsport.bfmtv.com/football/liga/fc-barcelone-real-madrid-en-direct-a-quelle-heure-et-sur-quelle-chaine-regarder-le-match-de-liga_AN-202605100019.html",
      "image": "https://images.bfmtv.com/q6F7Dd91_wl5G0t7PjSIaUExZOw=/0x0:1600x900/800x0/images/FC-Barcelone-Real-Madrid-en-direct-a-quelle-heure-et-sur-quelle-chaine-regarder-le-match-de-Liga-2281869.jpg",
      "date": "Sun, 10 May 2026 04:30:00 GMT",
      "time": "il y a 9h",
      "source": "RMC Sport",
      "sourceId": "rmc",
      "color": "#e05252",
      "cat": "Liga"
    }
  ],
  "scores": []
}